{"date":"2023-09-30T07:20:05.2670383+00:00","title":"fix crash","content":"fix crash\n","version":"0.1.2246","versionNumber":2246,"bds":"1.20.30","ll":"2.16.1","llnet":"2.16.1","url":"https://github.com/PixelFaramita/PixelFaramitaLuminousPolymerizationRes/releases/tag/v0.1.2246","files":[{"download":"https://github.com/PixelFaramita/PixelFaramitaLuminousPolymerizationRes/releases/download/v0.1.2246/LLNet_with_PFLP_Beta_v0.1.2246.zip","name":"LLNet_with_PFLP_Beta_v0.1.2246.zip","type":"application/zip","size":13655306,"update":"2023-09-30T07:20:05+00:00","path":["release","LLNet_with_PFLP_Beta_v0.1.2246.zip"]},{"download":"https://github.com/PixelFaramita/PixelFaramitaLuminousPolymerizationRes/releases/download/v0.1.2246/PFLP_Beta_v0.1.2246.dll","name":"PFLP_Beta_v0.1.2246.dll","type":"application/octet-stream","size":23345168,"update":"2023-09-30T07:20:00+00:00","path":["release","PFLP_Beta_v0.1.2246.dll"]}]}